vlm2vec_for_pyserini/__init__.py
vlm2vec_for_pyserini/arguments.py
vlm2vec_for_pyserini/logging_utils.py
vlm2vec_for_pyserini/loss.py
vlm2vec_for_pyserini/trainer.py
vlm2vec_for_pyserini/constant/__init__.py
vlm2vec_for_pyserini/constant/dataset_hf_path.py
vlm2vec_for_pyserini/constant/dataset_hflocal_path.py
vlm2vec_for_pyserini/data/__init__.py
vlm2vec_for_pyserini/data/collator/__init__.py
vlm2vec_for_pyserini/data/collator/eval_collator.py
vlm2vec_for_pyserini/data/collator/train_collator.py
vlm2vec_for_pyserini/data/dataset/__init__.py
vlm2vec_for_pyserini/data/dataset/base_pair_dataset.py
vlm2vec_for_pyserini/data/dataset/beir_dataset.py
vlm2vec_for_pyserini/data/dataset/berri.py
vlm2vec_for_pyserini/data/dataset/cls_dataset.py
vlm2vec_for_pyserini/data/dataset/didemo_dataset.py
vlm2vec_for_pyserini/data/dataset/docmatix_dataset.py
vlm2vec_for_pyserini/data/dataset/gui_dataset.py
vlm2vec_for_pyserini/data/dataset/hf_datasets.py
vlm2vec_for_pyserini/data/dataset/llavahound_dataset_caption.py
vlm2vec_for_pyserini/data/dataset/llavahound_dataset_qa.py
vlm2vec_for_pyserini/data/dataset/mmeb_dataset.py
vlm2vec_for_pyserini/data/dataset/msrvtt_dataset.py
vlm2vec_for_pyserini/data/dataset/msvd_dataset.py
vlm2vec_for_pyserini/data/dataset/mteb_cluster.py
vlm2vec_for_pyserini/data/dataset/mteb_training.py
vlm2vec_for_pyserini/data/dataset/pixmo.py
vlm2vec_for_pyserini/data/dataset/ssv2_dataset.py
vlm2vec_for_pyserini/data/dataset/text_dataset.py
vlm2vec_for_pyserini/data/dataset/videotext_dataset.py
vlm2vec_for_pyserini/data/dataset/vidore_dataset.py
vlm2vec_for_pyserini/data/dataset/visrag_dataset.py
vlm2vec_for_pyserini/data/eval_dataset/__init__.py
vlm2vec_for_pyserini/data/eval_dataset/activitynetqa_dataset.py
vlm2vec_for_pyserini/data/eval_dataset/base_eval_dataset.py
vlm2vec_for_pyserini/data/eval_dataset/didemo_dataset.py
vlm2vec_for_pyserini/data/eval_dataset/egoschema_dataset.py
vlm2vec_for_pyserini/data/eval_dataset/gui_dataset.py
vlm2vec_for_pyserini-0.2.0.dist-info/licenses/LICENSE
vlm2vec_for_pyserini-0.2.0.dist-info/METADATA
vlm2vec_for_pyserini-0.2.0.dist-info/WHEEL
vlm2vec_for_pyserini-0.2.0.dist-info/top_level.txt
vlm2vec_for_pyserini-0.2.0.dist-info/RECORD
