Metadata-Version: 2.4
Name: vlm2vec_for_pyserini
Version: 0.2.0
Summary: Fork of the original VLM2Vec repository modified for easy and simple Pyserini integration
Author-email: Ziyan Jiang <ziyanjiang528@gmail.com>, Rui Meng <memray0@gmail.com>, Wenhu Chen <wenhuchen@uwaterloo.ca>, Sahel Sharifymoghaddam <sahel.sharifymoghaddam@uwaterloo.ca>
Project-URL: Homepage, https://github.com/castorini/VLM2Vec-for-Pyserini
Project-URL: Bug Tracker, https://github.com/castorini/VLM2Vec-for-Pyserini/issues
Classifier: Programming Language :: Python :: 3
Classifier: License :: OSI Approved :: Apache Software License
Classifier: Operating System :: OS Independent
Requires-Python: >=3.12
License-File: LICENSE
Requires-Dist: accelerate
Requires-Dist: datasets
Requires-Dist: decord
Requires-Dist: einops
Requires-Dist: flash-attn
Requires-Dist: hjson
Requires-Dist: hnswlib
Requires-Dist: huggingface-hub
Requires-Dist: ninja
Requires-Dist: numpy
Requires-Dist: opencv-contrib-python
Requires-Dist: opencv-python
Requires-Dist: peft
Requires-Dist: pillow
Requires-Dist: py-cpuinfo
Requires-Dist: pytrec-eval
Requires-Dist: qwen-vl-utils[decord]==0.0.8
Requires-Dist: ray
Requires-Dist: scikit-image
Requires-Dist: scikit-learn
Requires-Dist: scipy
Requires-Dist: sentencepiece
Requires-Dist: timm
Requires-Dist: torch==2.9.1
Requires-Dist: torchvision
Requires-Dist: tqdm
Requires-Dist: transformers==4.51.3
Requires-Dist: wandb
Requires-Dist: wrapt
Dynamic: license-file
